{
    "username": "barkbark",
    "categories": 
    [
        {
            "name": "Studying",
            "content":
            [
                {
                    "name": "MSU",
                    "url": "https://www.msu.ru/"
                }
            ]
        },
        {
            "name": "Social",
            "content":
            [
                {
                    "name": "VK",
                    "url": "https://vk.com/"
                },
                {
                    "name": "YouTube",
                    "url": "https://www.youtube.com/"
                }
            ]
        }
    ]
}